akz/__init__.py
akz/cli.py
akz/transpiler.py
akz_lang-2.2.3.dist-info/METADATA
akz_lang-2.2.3.dist-info/WHEEL
akz_lang-2.2.3.dist-info/entry_points.txt
akz_lang-2.2.3.dist-info/top_level.txt
akz_lang-2.2.3.dist-info/RECORD
