Metadata-Version: 2.1
Name: akz-lang
Version: 2.2.3
Summary: Bahasa pemrograman AKZ untuk pemula
Home-page: https://akuzz.my.id/akz
Author: Azzam Jauzi
Author-email: bbb.azzam.jauzi@gmail.com
Classifier: Programming Language :: Python :: 3
Classifier: License :: OSI Approved :: MIT License
Classifier: Operating System :: OS Independent
Requires-Python: >=3.6
